.gitignore
.pre-commit-config.yaml
.pylintrc
ChangeLog.rst
README.rst
ROADMAP.rst
VERSION
make.sh
setup.py
setup.py.in
subpop.yaml
bin/blos
bin/blos-check
bin/deepdive
bin/deepquery
bin/direct-sync
bin/distfile-kit-fetch
bin/distfile-stats
bin/doit
bin/fastpull-daemon
bin/fastpull-daemon-ng
bin/fastpull-fixer
bin/fetch
bin/interkit-links
bin/list-kits
bin/mcafee-tool
bin/merge-gentoo-staging
bin/merge-kits
bin/missing-links
bin/prod-regen
bin/release-yaml-test
bin/reposcan
bin/storage-test
bin/test-metadata-extract
deprecated/mongo_backends.py
docs/Makefile
docs/autogen-dev.rst
docs/autogen.rst
docs/conf.py
docs/index.rst
docs/install.rst
docs/intro.rst
docs/meta-repo.rst
docs/_ext/consoleoutput.py
docs/_ext/_static/consoleoutput.css
docs/drafts/fastpull_object_store.rst
docs/drafts/repo_defs.rst
docs/features/dynamic-archives.rst
examples/reposcan.gentoo.yaml
funtoo/__init__.py
funtoo/pkgtools/__init__.py
funtoo/pkgtools/autogen.py
funtoo/pkgtools/ebuild.py
funtoo/pkgtools/fetch.py
funtoo/pkgtools/github.py
funtoo/pkgtools/golang.py
funtoo/pkgtools/http.py
funtoo/pkgtools/meson.py
funtoo/pkgtools/pages.py
funtoo/pkgtools/pyhelper.py
funtoo/pkgtools/rust.py
funtoo_metatools.egg-info/PKG-INFO
funtoo_metatools.egg-info/SOURCES.txt
funtoo_metatools.egg-info/dependency_links.txt
funtoo_metatools.egg-info/requires.txt
funtoo_metatools.egg-info/top_level.txt
metatools/__init__.py
metatools/blos.py
metatools/cmd.py
metatools/context.py
metatools/fetch_cache.py
metatools/hashutils.py
metatools/kit.py
metatools/kit_cache.py
metatools/metadata.py
metatools/model.py
metatools/pretty_logging.py
metatools/release.py
metatools/steps.py
metatools/store.py
metatools/tree.py
metatools/version.py
metatools/yaml_util.py
metatools/config/__init__.py
metatools/config/autogen.py
metatools/config/base.py
metatools/config/merge.py
metatools/config/mongodb.py
metatools/fastpull/__init__.py
metatools/fastpull/core.py
metatools/fastpull/spider.py
metatools/generator/__init__.py
metatools/generator/common.py
metatools/generator/transform.py
metatools/version/__init__.py
metatools/version/base.py
metatools/version/generic.py
metatools/zmq/__init__.py
metatools/zmq/app_core.py
