Metadata-Version: 2.1
Name: funtoo-metatools
Version: 1.3.7
Summary: Funtoo framework for auto-creation of ebuilds.
Home-page: https://code.funtoo.org/bitbucket/users/drobbins/repos/funtoo-metatools/browse
Author: Daniel Robbins
Author-email: drobbins@funtoo.org
Classifier: Programming Language :: Python :: 3
Classifier: License :: OSI Approved :: Apache Software License
Classifier: Operating System :: POSIX :: Linux
Requires-Python: >=3.7
Requires-Dist: subpop>=2.0.0
Requires-Dist: beautifulsoup4
Requires-Dist: dict_toolbox
Requires-Dist: httpx[http2]
Requires-Dist: Jinja2>=3
Requires-Dist: packaging
Requires-Dist: psutil
Requires-Dist: pymongo
Requires-Dist: PyYAML
Requires-Dist: pyzmq
Requires-Dist: rich
Requires-Dist: toml
Requires-Dist: xmltodict
Requires-Dist: colorama
